runp/__init__.py
runp/runp.py
tests/__init__.py
tests/test.py
tests/testfile.py
pyrunp-0.0.3.dist-info/METADATA
pyrunp-0.0.3.dist-info/WHEEL
pyrunp-0.0.3.dist-info/entry_points.txt
pyrunp-0.0.3.dist-info/top_level.txt
pyrunp-0.0.3.dist-info/RECORD
