Metadata-Version: 2.1
Name: pyrunp
Version: 0.0.3
Summary: pyrunp exports Python functions from files to the command line
Home-page: https://github.com/alex-testlab/pyrunp
Author: alex
Author-email: 
Classifier: Environment :: Console
Classifier: Intended Audience :: Developers
Classifier: Programming Language :: Python
Classifier: Topic :: Software Development
